SynBPS/dataprep/__init__.py
SynBPS/dataprep/dataprep_helperfunctions.py
SynBPS/dataprep/prepare.py
SynBPS/dataprep/transformer_loader.py
SynBPS/design/DoE.py
SynBPS/design/__init__.py
SynBPS/simulation/__init__.py
SynBPS/simulation/alg6_memoryless_process_generator.py
SynBPS/simulation/alg7_memory_process_generator.py
SynBPS/simulation/simulate_eventlog.py
SynBPS/simulation/simulation_helpers.py
SynBPS/simulation/simulation_pipeline.py
SynBPS/simulation/Arrival/alg1_trace_arrivals.py
SynBPS/simulation/Duration/__init__.py
SynBPS/simulation/Duration/alg9_trace_durations.py
SynBPS/simulation/Duration/duration_helpers.py
SynBPS/simulation/Memory_process/MarkovChain.py
SynBPS/simulation/Memory_process/__init__.py
SynBPS/simulation/Memory_process/distributions/ConditionalProbabilityTable.py
SynBPS/simulation/Memory_process/distributions/DiscreteDistribution.py
SynBPS/simulation/Memory_process/distributions/Distribution.py
SynBPS/simulation/Memory_process/distributions/JointProbabilityTable.py
SynBPS/simulation/Memory_process/distributions/__init__.py
SynBPS/simulation/Memoryless_process/__init__.py
SynBPS/simulation/Memoryless_process/alg2_initial_probabilities.py
SynBPS/simulation/Memoryless_process/alg3_transition_matrix_min_entropy.py
SynBPS/simulation/Memoryless_process/alg4_transition_matrix_max_entropy.py
SynBPS/simulation/Memoryless_process/alg5_transition_matrix_med_entropy.py
SynBPS-1.1.3.dist-info/LICENSE
SynBPS-1.1.3.dist-info/METADATA
SynBPS-1.1.3.dist-info/WHEEL
SynBPS-1.1.3.dist-info/top_level.txt
SynBPS-1.1.3.dist-info/RECORD
