Metadata-Version: 2.1
Name: SynBPS
Version: 1.1.3
Summary: Synthetic Business Process Simulation
Author-email: Mike Riess <mike@riess.no>
Project-URL: Homepage, https://github.com/mikeriess/synbps
Project-URL: Issues, https://github.com/mikeriess/synbps/issues
Classifier: Programming Language :: Python :: 3
Classifier: License :: OSI Approved :: MIT License
Classifier: Operating System :: OS Independent
Requires-Python: >=3.9
License-File: LICENSE
Requires-Dist: numpy >=1.26.2
Requires-Dist: pandas ==2.1.4
Requires-Dist: scipy >=1.7.0
Requires-Dist: networkx ==2.6.2
Requires-Dist: tqdm ==4.66.3
